csspin_docs/sphinx.py
csspin_docs/sphinx_schema.yaml
csspin_docs-2.0.0.dist-info/licenses/LICENSE
csspin_docs-2.0.0.dist-info/METADATA
csspin_docs-2.0.0.dist-info/WHEEL
csspin_docs-2.0.0.dist-info/top_level.txt
csspin_docs-2.0.0.dist-info/RECORD
