Metadata-Version: 2.4
Name: csspin-docs
Version: 2.0.0
Summary: Plugin-package for csspin providing documentation-build related plugins
Author-email: CONTACT Software GmbH <info@contact-software.com>
Maintainer-email: Waleri Enns <waleri.enns@contact-software.com>, Benjamin Thomas Schwertfeger <benjaminthomas.schwertfeger@contact-software.com>, Fabian Hafer <fabian.hafer@contact-software.com>
License-Expression: Apache-2.0
Project-URL: Homepage, https://contact-software.com
Classifier: Environment :: Console
Classifier: Development Status :: 5 - Production/Stable
Classifier: Intended Audience :: Developers
Classifier: Operating System :: OS Independent
Classifier: Programming Language :: Python :: 3
Classifier: Programming Language :: Python :: 3.9
Classifier: Programming Language :: Python :: 3.10
Classifier: Programming Language :: Python :: 3.11
Classifier: Programming Language :: Python :: 3.12
Classifier: Programming Language :: Python :: 3.13
Classifier: Topic :: Software Development
Requires-Python: >=3.9
License-File: LICENSE
Requires-Dist: csspin-python
Dynamic: license-file
